_private/__init__.py
_private/generic.py
_private/property.py
_private/serializable.py
_private/tee_file.py
simfile/__init__.py
simfile/base.py
simfile/convert.py
simfile/notes.py
simfile/py.typed
simfile/sm.py
simfile/ssc.py
simfile/timing.py
simfile/types.py
simfile/_private/__init__.py
simfile/_private/dedent.py
simfile/_private/generic.py
simfile/_private/property.py
simfile/_private/serializable.py
simfile/_private/tee_file.py
simfile/notes/__init__.py
simfile/notes/count.py
simfile/notes/group.py
simfile/notes/timed.py
simfile/notes/transform.py
simfile/timing/__init__.py
simfile/timing/displaybpm.py
simfile/timing/engine.py
simfile/timing/_private/__init__.py
simfile/timing/_private/sscproxy.py
simfile/timing/_private/timingsource.py
tests/__init__.py
tests/test_module.py
tests/test_simfile.py
tests/test_sm.py
tests/test_ssc.py
simfile-2.0.1.dist-info/LICENSE.md
simfile-2.0.1.dist-info/METADATA
simfile-2.0.1.dist-info/WHEEL
simfile-2.0.1.dist-info/top_level.txt
simfile-2.0.1.dist-info/RECORD
