Metadata-Version: 2.1
Name: simfile
Version: 2.0.1
Summary: Modern simfile library for Python
Home-page: https://github.com/garcia/simfile
Author: Ash Garcia
Author-email: python-simfile@garcia.sh
License: MIT
Keywords: stepmania simfile sm ssc
Platform: UNKNOWN
Classifier: Development Status :: 3 - Alpha
Classifier: Programming Language :: Python :: 3
Classifier: Topic :: Games/Entertainment
Classifier: Topic :: Software Development :: Libraries :: Python Modules
Classifier: Typing :: Typed
Requires-Python: >=3.6
Requires-Dist: msdparser (~=1.0.0)
